gemma_permifrost-0.1.3.dist-info/licenses/LICENSE
permifrost/__init__.py
permifrost/entities.py
permifrost/error.py
permifrost/logger.py
permifrost/snowflake_connector.py
permifrost/snowflake_grants.py
permifrost/snowflake_permission.py
permifrost/snowflake_role_grant_checker.py
permifrost/snowflake_spec_loader.py
permifrost/spec_file_loader.py
permifrost/types.py
permifrost/cli/__init__.py
permifrost/cli/__main__.py
permifrost/cli/cli.py
permifrost/cli/permissions.py
permifrost/spec_schemas/__init__.py
permifrost/spec_schemas/snowflake.py
gemma_permifrost-0.1.3.dist-info/METADATA
gemma_permifrost-0.1.3.dist-info/WHEEL
gemma_permifrost-0.1.3.dist-info/entry_points.txt
gemma_permifrost-0.1.3.dist-info/top_level.txt
gemma_permifrost-0.1.3.dist-info/RECORD
