Metadata-Version: 2.4
Name: gemma.permifrost
Version: 0.1.3
Summary: Permifrost Permissions - Fork by Gemma Analytics
Home-page: https://github.com/Gemma-Analytics/permifrost
Author: Gemma Analytics
Author-email: Gemma Analytics <info@gemmaanalytics.com>
Maintainer-email: Gemma Analytics <info@gemmaanalytics.com>
License: MIT
Project-URL: Homepage, https://github.com/Gemma-Analytics/permifrost
Project-URL: Repository, https://github.com/Gemma-Analytics/permifrost
Project-URL: Documentation, https://github.com/Gemma-Analytics/permifrost
Project-URL: Issues, https://github.com/Gemma-Analytics/permifrost/issues
Keywords: snowflake,permissions,database,security
Classifier: Development Status :: 4 - Beta
Classifier: Intended Audience :: Developers
Classifier: License :: OSI Approved :: MIT License
Classifier: Operating System :: OS Independent
Classifier: Programming Language :: Python :: 3
Classifier: Programming Language :: Python :: 3.8
Classifier: Programming Language :: Python :: 3.9
Classifier: Programming Language :: Python :: 3.10
Classifier: Programming Language :: Python :: 3.11
Classifier: Topic :: Database
Classifier: Topic :: Security
Requires-Python: >=3.8
License-File: LICENSE
Requires-Dist: cerberus
Requires-Dist: colorama
Requires-Dist: coloredlogs
Requires-Dist: click==8.0.1
Requires-Dist: click-default-group
Requires-Dist: pyyaml
Requires-Dist: snowflake-connector-python[secure-local-storage]
Requires-Dist: snowflake-sqlalchemy==1.5.3
Requires-Dist: sqlalchemy
Provides-Extra: dev
Requires-Dist: black==22.3.0; extra == "dev"
Requires-Dist: bumpversion; extra == "dev"
Requires-Dist: build; extra == "dev"
Requires-Dist: changelog-cli; extra == "dev"
Requires-Dist: coverage; extra == "dev"
Requires-Dist: flake8; extra == "dev"
Requires-Dist: isort; extra == "dev"
Requires-Dist: mypy; extra == "dev"
Requires-Dist: pre-commit; extra == "dev"
Requires-Dist: pytest==6.2.5; extra == "dev"
Requires-Dist: pytest-cov==2.12.1; extra == "dev"
Requires-Dist: pytest-mock==3.6.1; extra == "dev"
Requires-Dist: twine; extra == "dev"
Requires-Dist: types-PyYAML; extra == "dev"
Dynamic: author
Dynamic: home-page
Dynamic: license-file
